krbjack/__init__.py
krbjack/__main__.py
krbjack/custompipes.py
krbjack/krbjacker.py
krbjack/modules/__init__.py
krbjack/modules/krboversmb.py
krbjack/modules/utils.py
krbjack/tcpforward.py
krbjack/utils.py
krbjack-1.2.0.dist-info/entry_points.txt
krbjack-1.2.0.dist-info/LICENSE
krbjack-1.2.0.dist-info/METADATA
krbjack-1.2.0.dist-info/WHEEL
krbjack-1.2.0.dist-info/RECORD
