Metadata-Version: 2.1
Name: krbjack
Version: 1.2.0
Summary: Kerberos AP-REQ hijacking tool with DNS unsecure updates abuse.
Home-page: https://github.com/almandin/krbjack
License: Beerware
Author: Virgile Jarry
Author-email: virgile@mailbox.org
Requires-Python: >=3.9,<4.0
Classifier: License :: Other/Proprietary License
Classifier: Programming Language :: Python :: 3
Classifier: Programming Language :: Python :: 3.9
Classifier: Programming Language :: Python :: 3.10
Classifier: Programming Language :: Python :: 3.11
Requires-Dist: colorama (>=0.4.4,<0.5.0)
Requires-Dist: dnspython (>=2.0.0,<3.0.0)
Requires-Dist: impacket (>=0.10.0,<0.11.0)
Requires-Dist: scapy (>=2.5.0,<3.0.0)
Project-URL: Documentation, https://github.com/almandin/krbjack/README.md
Project-URL: Repository, https://github.com/almandin/krbjack
